{
    "Length": {
        "devacc": 57.9,
        "acc": 57.7,
        "ndev": 1000,
        "ntest": 1000
    },
    "Depth": {
        "devacc": 27.4,
        "acc": 27.7,
        "ndev": 1000,
        "ntest": 1000
    },
    "TopConstituents": {
        "devacc": 63.7,
        "acc": 62.7,
        "ndev": 1000,
        "ntest": 1000
    },
    "BigramShift": {
        "devacc": 84.5,
        "acc": 82.0,
        "ndev": 1000,
        "ntest": 1000
    },
    "Tense": {
        "devacc": 90.4,
        "acc": 87.0,
        "ndev": 1000,
        "ntest": 1000
    },
    "SubjNumber": {
        "devacc": 81.3,
        "acc": 79.2,
        "ndev": 1000,
        "ntest": 1000
    },
    "ObjNumber": {
        "devacc": 72.1,
        "acc": 74.5,
        "ndev": 1000,
        "ntest": 1000
    },
    "OddManOut": {
        "devacc": 63.5,
        "acc": 61.0,
        "ndev": 1000,
        "ntest": 1000
    },
    "CoordinationInversion": {
        "devacc": 67.4,
        "acc": 65.1,
        "ndev": 1000,
        "ntest": 1000
    }
}